pydglab/__init__.py
pydglab/bthandler_v2.py
pydglab/bthandler_v3.py
pydglab/model_v2.py
pydglab/model_v3.py
pydglab/service.py
pydglab/uuid.py
pydglab-1.0.0.dist-info/LICENSE
pydglab-1.0.0.dist-info/METADATA
pydglab-1.0.0.dist-info/WHEEL
pydglab-1.0.0.dist-info/RECORD
